gslides_automator/__init__.py
gslides_automator/__main__.py
gslides_automator/auth.py
gslides_automator/cli.py
gslides_automator/drive_layout.py
gslides_automator/generate.py
gslides_automator/l1_generate.py
gslides_automator/l2_generate.py
gslides_automator/l3_generate.py
gslides_automator-0.5.0.dist-info/licenses/LICENSE.txt
gslides_automator-0.5.0.dist-info/METADATA
gslides_automator-0.5.0.dist-info/WHEEL
gslides_automator-0.5.0.dist-info/entry_points.txt
gslides_automator-0.5.0.dist-info/top_level.txt
gslides_automator-0.5.0.dist-info/RECORD
